lynx/kite.py
lynx/steiner.py
lynx/proto/dapcstp_pb2.py
lynx/proto/dapcstp_pb2_grpc.py
lynx/proto/x.py
lynxkite_fiber_python_api-2.8.3.dist-info/METADATA
lynxkite_fiber_python_api-2.8.3.dist-info/WHEEL
lynxkite_fiber_python_api-2.8.3.dist-info/top_level.txt
lynxkite_fiber_python_api-2.8.3.dist-info/RECORD
